MANIFEST.in
README.rst
setup.cfg
setup.py
examples/.process_client.py.swp
examples/process_client.py
iotlabmqtt/__init__.py
iotlabmqtt/asyncconnection.py
iotlabmqtt/common.py
iotlabmqtt/iotlabapi.py
iotlabmqtt/mqttcommon.py
iotlabmqtt/node.py
iotlabmqtt/process.py
iotlabmqtt/processcommon.py
iotlabmqtt/radiosniffer.py
iotlabmqtt/serial.py
iotlabmqtt.egg-info/PKG-INFO
iotlabmqtt.egg-info/SOURCES.txt
iotlabmqtt.egg-info/dependency_links.txt
iotlabmqtt.egg-info/entry_points.txt
iotlabmqtt.egg-info/requires.txt
iotlabmqtt.egg-info/top_level.txt
iotlabmqtt/clients/__init__.py
iotlabmqtt/clients/common.py
iotlabmqtt/clients/log.py
iotlabmqtt/clients/node.py
iotlabmqtt/clients/process.py
iotlabmqtt/clients/radiosniffer.py
iotlabmqtt/clients/serial.py
iotlabmqtt/tests/__init__.py
iotlabmqtt/tests/clients_common_tests.py
iotlabmqtt/tests/iotlabapi_tests.py
iotlabmqtt/tests/mqttclient_mock.py
iotlabmqtt/tests/mqttcommon_tests.py
iotlabmqtt/tests/serial_tests.py
iotlabmqtt/tests/integration_tests/__init__.py
iotlabmqtt/tests/integration_tests/log_integration_test.py
iotlabmqtt/tests/integration_tests/node_integration_test.py
iotlabmqtt/tests/integration_tests/process_integration_test.py
iotlabmqtt/tests/integration_tests/radiosniffer_integration_test.py
iotlabmqtt/tests/integration_tests/serial_integration_test.py
iotlabmqtt/tests/integration_tests/files/echo_stderr.sh
iotlabmqtt/tests/integration_tests/files/m3_firmware.elf
iotlabmqtt/tests/integration_tests/files/print_one_line.py
iotlabmqtt/tests/integration_tests/files/print_stdout.sh
iotlabmqtt/tests/integration_tests/files/trap_sigterm.sh