Metadata-Version: 1.1
Name: iotlabmqtt
Version: 0.6.2
Summary: Provide access to IoT-LAB experiments as MQTT agents
Home-page: http://www.iot-lab.info
Author: IoT-LAB Team
Author-email: admin@iot-lab.info
License: CeCILL v2.1
Download-URL: http://github.com/iot-lab/iot-lab-mqtt/
Platform: UNKNOWN
Classifier: Development Status :: 3 - Alpha
Classifier: Programming Language :: Python
Classifier: Programming Language :: Python :: 2.7
Classifier: Programming Language :: Python :: 3
Classifier: Environment :: Console
Classifier: Topic :: Utilities
